pysyzygy/Makefile
pysyzygy/__init__.py
pysyzygy/plot.py
pysyzygy/transit.c
pysyzygy/transit.h
pysyzygy/transit.py
pysyzygy-0.0.2.dist-info/METADATA
pysyzygy-0.0.2.dist-info/RECORD
pysyzygy-0.0.2.dist-info/WHEEL
pysyzygy-0.0.2.dist-info/top_level.txt
