Metadata-Version: 1.1
Name: pysyzygy
Version: 0.0.2
Summary: Transit modeling in Python
Home-page: http://github.com/rodluger/pysyzygy
Author: Rodrigo Luger
Author-email: rodluger@uw.edu
License: MIT
Keywords: exoplanets transits
Platform: UNKNOWN
Classifier: Development Status :: 3 - Alpha
Classifier: License :: OSI Approved :: MIT License
Classifier: Programming Language :: Python
Classifier: Programming Language :: Python :: 3
Classifier: Topic :: Scientific/Engineering :: Astronomy
